{
    "paginator": {
        "use": [
            "paginator-base"
        ],

        "lang": [
            "en"
        ],

        "skinnable": true,

        "submodules": {
            "paginator-base": {
                "requires": [
                    "view",
                    "paginator-core",
                    "paginator-url",
                    "classnamemanager",
                    "template",
                    "intl"
                ],
                "lang": [
                    "en"
                ]
            },
            "paginator-core": {
                "requires": [
                    "base"
                ]
            },
            "paginator-url": {
                "requires": []
            },
            "paginator-list": {
                "requires": [
                    "paginator"
                ]
            }
        }
    }
}

